vaultik/__init__.py
vaultik/client.py
vaultik/exceptions.py
vaultik_api_client-1.1.0.dist-info/METADATA
vaultik_api_client-1.1.0.dist-info/WHEEL
vaultik_api_client-1.1.0.dist-info/top_level.txt
vaultik_api_client-1.1.0.dist-info/RECORD
